e621_data/__init__.py
e621_data/posts.py
e621_data/tag_aliases.py
e621_data/tag_implications.py
e621_data/tags.py
e621_data/utils.py
e621_data-1.0.0.dist-info/LICENSE
e621_data-1.0.0.dist-info/WHEEL
e621_data-1.0.0.dist-info/METADATA
e621_data-1.0.0.dist-info/RECORD
